{
  "bindings": [
    {
      "type": "eventHubTrigger",
      "name": "myEventHubMessage",
      "direction": "in",
      "path": "insights-logs-networksecuritygroupevent",
      "connection": "NsgEvents",
      "consumerGroup": "$Default",
      "cardinality": "one"
    },
    {
      "type": "table",
      "name": "nsgEventStatsTableOut",
      "tableName": "NsgEventStats",
      "connection": "AzureWebJobsStorage",
      "direction": "out"
    },
    {
      "type": "table",
      "name": "inputTable",
      "tableName": "DatacenterIpRanges",
      "connection": "AzureWebJobsStorage",
      "direction": "in"
    },
    {
      "type": "table",
      "name": "nsgEventStatsTableIn",
      "tableName": "NsgEventStats",
      "connection": "AzureWebJobsStorage",
      "direction": "in"
    }
  ],
  "disabled": false
}